qrev_email_verification/__init__.py
qrev_email_verification/email_verification.py
qrev_email_verification/email_verifying_service.py
qrev_email_verification/models/models.py
qrev_email_verification/py.typed
qrev_email_verification/services/millionverifier/api.py
qrev_email_verification/services/millionverifier/models.py
qrev_email_verification/services/millionverifier/mongo_api.py
qrev_email_verification/services/zerobounce/api.py
qrev_email_verification/services/zerobounce/models.py
qrev_email_verification/services/zerobounce/mongo_api.py
qrev_email_verification-0.2.1.3.dist-info/METADATA
qrev_email_verification-0.2.1.3.dist-info/WHEEL
qrev_email_verification-0.2.1.3.dist-info/RECORD
